dash_entrypoints/__init__.py
dash_entrypoints/misc.py
dash_entrypoints/assets/__init__.py
dash_entrypoints/assets/dropdown.fix.css
dash_entrypoints/elements/__init__.py
dash_entrypoints/elements/popup_for_information.py
dash_entrypoints/elements/table_for_editing.py
dash_entrypoints/elements/table_for_selection.py
dash_entrypoints/elements/table_layout_wrapper.py
dash_entrypoints/elements/table_with_dropdown.py
dash_entrypoints/multi_page/__init__.py
dash_entrypoints/multi_page/cli.py
dash_entrypoints/multi_page/entrypoint.py
dash_entrypoints/plugins/__init__.py
dash_entrypoints/plugins/minimalplugin.py
dash_entrypoints/views/__init__.py
dash_entrypoints/views/add__example_callback_wrapper_dropdown.py
dash_entrypoints/views/add__example_callback_wrapper_edit_table.py
dash_entrypoints/views/add__example_callback_wrapper_selection.py
dash_entrypoints/views/add__example_popup_for_info.py
dash_entrypoints/views/add__example_table_dropdown.py
dash_entrypoints/views/add__example_table_edit_table.py
dash_entrypoints/views/add__example_table_selection.py
dash_entrypoints/views/show__example_page.py
dash_entrypoints-0.2.3.dist-info/LICENSE
dash_entrypoints-0.2.3.dist-info/METADATA
dash_entrypoints-0.2.3.dist-info/WHEEL
dash_entrypoints-0.2.3.dist-info/entry_points.txt
dash_entrypoints-0.2.3.dist-info/top_level.txt
dash_entrypoints-0.2.3.dist-info/RECORD
