Metadata-Version: 2.1
Name: dash-entrypoints
Version: 0.2.3
Summary: Dash entrypoints: Wrapper for dash/dash-labs multi-page app and specific layout elements.
Author: Lars B. Rollik
Author-email: L.B.ROLLIK@protonmail.com
License: BSD 3-Clause License        
Platform: UNKNOWN
Requires-Python: >=3.6
License-File: LICENSE
Requires-Dist: dash
Requires-Dist: dash-bootstrap-components
Requires-Dist: dash-labs (==1.0.2)
Requires-Dist: rich
Provides-Extra: dev
Requires-Dist: black ; extra == 'dev'
Requires-Dist: pytest-cov ; extra == 'dev'
Requires-Dist: pytest ; extra == 'dev'
Requires-Dist: gitpython ; extra == 'dev'
Requires-Dist: coverage (>=5.0.3) ; extra == 'dev'
Requires-Dist: bump2version ; extra == 'dev'
Requires-Dist: pre-commit ; extra == 'dev'
Requires-Dist: flake8 ; extra == 'dev'
